pyramid_transactional_celery/__init__.py
pyramid_transactional_celery/transactional_task.py
pyramid_transactional_celery-0.1.1.dist-info/DESCRIPTION.rst
pyramid_transactional_celery-0.1.1.dist-info/METADATA
pyramid_transactional_celery-0.1.1.dist-info/metadata.json
pyramid_transactional_celery-0.1.1.dist-info/RECORD
pyramid_transactional_celery-0.1.1.dist-info/top_level.txt
pyramid_transactional_celery-0.1.1.dist-info/WHEEL
