Metadata-Version: 2.0
Name: pyramid-transactional-celery
Version: 0.1.1
Summary: A transaction-aware Celery job setup
Home-page: https://github.com/petrilli/pyramid_transactional_celery
Author: Christopher Petrilli
Author-email: petrilli@amber.org
License: BSD
Keywords: pyramid_transactional_celery
Platform: UNKNOWN
Classifier: Development Status :: 2 - Pre-Alpha
Classifier: Intended Audience :: Developers
Classifier: License :: OSI Approved :: BSD License
Classifier: Natural Language :: English
Classifier: Programming Language :: Python :: 2
Classifier: Programming Language :: Python :: 2.7
Classifier: Programming Language :: Python :: 3
Classifier: Programming Language :: Python :: 3.3
Classifier: Programming Language :: Python :: 3.4
Requires-Dist: transaction
